sfctools/__init__.py
sfctools/__main__.py
sfctools/automation/__init__.py
sfctools/automation/calibration.py
sfctools/automation/cgesolver.py
sfctools/automation/README.md
sfctools/automation/runner.py
sfctools/bottomup/__init__.py
sfctools/bottomup/matching.py
sfctools/bottomup/productiontree.py
sfctools/bottomup/stock_manager.py
sfctools/bottomup/treestruct.py
sfctools/core/__init__.py
sfctools/core/agent.py
sfctools/core/balance_matrix.py
sfctools/core/clock.py
sfctools/core/custom_warnings.py
sfctools/core/flow_matrix.py
sfctools/core/settings.py
sfctools/core/singleton.py
sfctools/core/world.py
sfctools/datastructs/__init__.py
sfctools/datastructs/balance.py
sfctools/datastructs/bank_order_book.py
sfctools/datastructs/cash_flow_statement.py
sfctools/datastructs/collection.py
sfctools/datastructs/income_statement.py
sfctools/datastructs/inventory.py
sfctools/datastructs/market_registry.py
sfctools/datastructs/signalslot.py
sfctools/datastructs/worker_registry.py
sfctools/examples/__init__.py
sfctools/examples/balance.py
sfctools/examples/basic_example/basic_example.py
sfctools/examples/basic_example/my_settings.yml
sfctools/examples/clock.py
sfctools/examples/example_wrapper.py
sfctools/examples/exampleabm/agents/__init__.py
sfctools/examples/exampleabm/agents/government.py
sfctools/examples/exampleabm/agents/household.py
sfctools/examples/exampleabm/agents/production.py
sfctools/examples/exampleabm/agents/transactions.py
sfctools/examples/exampleabm/data/preprocess.py
sfctools/examples/exampleabm/data/processed/tipsau20_gdp_processed.txt
sfctools/examples/exampleabm/data/raw/tipsau20_gdp.csv
sfctools/examples/exampleabm/figures/matrix.png
sfctools/examples/exampleabm/figures/outputs.png
sfctools/examples/exampleabm/figures/sankey.png
sfctools/examples/exampleabm/info.md
sfctools/examples/exampleabm/model.py
sfctools/examples/exampleabm/settings.yml
sfctools/examples/flowmatrix.py
sfctools/examples/hello_agent.py
sfctools/examples/inventory.py
sfctools-1.1.9.2.dist-info/LICENSE
sfctools-1.1.9.2.dist-info/METADATA
sfctools-1.1.9.2.dist-info/WHEEL
sfctools-1.1.9.2.dist-info/RECORD
