Metadata-Version: 2.1
Name: sfctools
Version: 1.1.9.2
Summary: Framework for stock-flow consistent agent-based modeling, being developed at the German Aerospace Center (DLR) for and in the scientific context of energy systems analysis, however, it is widely applicable in other scientific fields.
Home-page: https://gitlab.com/dlr-ve/esy/sfctools/framework
License: MIT
Keywords: stock-flow-consistent,agent-based,agent,macroeconomics,computational economics
Author: Thomas Baldauf
Author-email: thomas.baldauf@dlr.de
Maintainer: Thomas Baldauf, Benjamin Fuchs
Maintainer-email: thomas.baldauf@dlr.de, benjamin.fuchs@dlr.de
Requires-Python: >=3.6,<=3.12
Classifier: License :: OSI Approved :: MIT License
Classifier: Programming Language :: Python :: 3
Classifier: Programming Language :: Python :: 3.6
Classifier: Programming Language :: Python :: 3.7
Classifier: Programming Language :: Python :: 3.8
Classifier: Programming Language :: Python :: 3.9
Classifier: Programming Language :: Python :: 3.10
Classifier: Programming Language :: Python :: 3.11
Requires-Dist: PyQt5 (>=5.9)
Requires-Dist: attrs
Requires-Dist: graphviz
Requires-Dist: matplotlib (>=2.0.0)
Requires-Dist: networkx (>=2.2)
Requires-Dist: numpy
Requires-Dist: openpyxl
Requires-Dist: pandas
Requires-Dist: pyperclip (>=1.5.0)
Requires-Dist: pytest-cov
Requires-Dist: pytest-qt
Requires-Dist: pyyaml (>=3.0.3)
Requires-Dist: scipy (>1.9.1)
Requires-Dist: seaborn
Requires-Dist: setuptools (>=50.0.0)
Requires-Dist: sympy (>=1.10.0)
Project-URL: Documentation, https://sfctools-framework.readthedocs.io/en/latest/
